telebot/__init__.py
telebot/apihelper.py
telebot/async_telebot.py
telebot/asyncio_filters.py
telebot/asyncio_handler_backends.py
telebot/asyncio_helper.py
telebot/callback_data.py
telebot/custom_filters.py
telebot/handler_backends.py
telebot/types.py
telebot/util.py
telebot/version.py
telebot_kor0p-4.2.2.dist-info/LICENSE
telebot_kor0p-4.2.2.dist-info/METADATA
telebot_kor0p-4.2.2.dist-info/WHEEL
telebot_kor0p-4.2.2.dist-info/top_level.txt
telebot_kor0p-4.2.2.dist-info/RECORD
