Metadata-Version: 2.1
Name: telebot-kor0p
Version: 4.2.2
Summary: Python Telegram bot api. 
Home-page: https://github.com/eternnoir/pyTelegramBotAPI
Author: eternnoir
Author-email: eternnoir@gmail.com
License: GPL2
Keywords: telegram bot api tools
Platform: UNKNOWN
Classifier: Development Status :: 5 - Production/Stable
Classifier: Programming Language :: Python :: 3
Classifier: Environment :: Console
Classifier: License :: OSI Approved :: GNU General Public License v2 (GPLv2)
License-File: LICENSE
Requires-Dist: requests
Provides-Extra: pil
Requires-Dist: Pillow ; extra == 'pil'
Provides-Extra: json
Requires-Dist: ujson ; extra == 'json'
Provides-Extra: redis
Requires-Dist: redis (>=3.4.1) ; extra == 'redis'
